varcall/__about__.py
varcall/__init__.py
varcall/__main__.py
varcall/app.css
varcall/app.py
varcall/components/__init__.py
varcall/components/file_suggester.py
varcall/components/input_block.py
varcall/components/yes_or_no.py
varcall/help/__init__.py
varcall/help/help.md
varcall/process/__init__.py
varcall/process/process_class.py
varcall/process/process_dict.py
varcall-2.0.1.dist-info/METADATA
varcall-2.0.1.dist-info/WHEEL
varcall-2.0.1.dist-info/entry_points.txt
varcall-2.0.1.dist-info/licenses/LICENSE
varcall-2.0.1.dist-info/RECORD
