Metadata-Version: 2.4
Name: varcall
Version: 2.0.1
Summary: A beginner friendly TUI tool for variant calling
Project-URL: Documentation, https://github.com/vidyasagar0405/varcall#readme
Project-URL: Issues, https://github.com/vidyasagar0405/varcall/issues
Project-URL: Source, https://github.com/vidyasagar0405/varcall
Author-email: vidyasagar0405 <vidyasagar0405@gmail.com>
License-Expression: MIT
License-File: LICENSE
Classifier: Development Status :: 2 - Pre-Alpha
Classifier: Programming Language :: Python
Classifier: Programming Language :: Python :: 3.8
Classifier: Programming Language :: Python :: 3.9
Classifier: Programming Language :: Python :: 3.10
Classifier: Programming Language :: Python :: 3.11
Classifier: Programming Language :: Python :: 3.12
Classifier: Programming Language :: Python :: Implementation :: CPython
Classifier: Programming Language :: Python :: Implementation :: PyPy
Requires-Python: >=3.8
Requires-Dist: textual
